django_expr/__init__.py
django_expr/apps.py
django_expr/expression.py
django_expr/templatetags.py
django_expr/templatetags/__init__.py
django_expr/templatetags/expr.py
django_expr-0.1.0.dist-info/LICENSE
django_expr-0.1.0.dist-info/METADATA
django_expr-0.1.0.dist-info/WHEEL
django_expr-0.1.0.dist-info/top_level.txt
django_expr-0.1.0.dist-info/RECORD
