Metadata-Version: 2.1
Name: django_expr
Version: 0.1.0
Summary: Django template tag and filter for evaluating Python expressions
Author-email: Juro Oravec <juraj.oravec.josefson@gmail.com>
License: MIT
Project-URL: Homepage, https://github.com/JuroOravec/alpinui/blob/main/packages/django-expr
Keywords: django,python,expression,django tag,django filter
Classifier: Framework :: Django
Classifier: Framework :: Django :: 4.2
Classifier: Framework :: Django :: 5.0
Classifier: Operating System :: OS Independent
Classifier: Programming Language :: Python
Classifier: Programming Language :: Python :: 3
Classifier: Programming Language :: Python :: 3.8
Classifier: Programming Language :: Python :: 3.9
Classifier: Programming Language :: Python :: 3.10
Classifier: Programming Language :: Python :: 3.11
Classifier: Programming Language :: Python :: 3.12
Requires-Python: <4.0,>=3.8
License-File: LICENSE
Requires-Dist: Django >=4.2
